nanika.py
nanika-0.1.1.dist-info/METADATA
nanika-0.1.1.dist-info/WHEEL
nanika-0.1.1.dist-info/entry_points.txt
nanika-0.1.1.dist-info/top_level.txt
nanika-0.1.1.dist-info/RECORD
