Metadata-Version: 2.1
Name: nanika
Version: 0.1.1
Summary: nanika
Author: yui sugawara
Author-email: s2222049@stu.musashino-u.ac.jp
License: MIT
Classifier: Programming Language :: Python :: 3
Classifier: License :: OSI Approved :: MIT License
Classifier: Operating System :: OS Independent
Requires-Python: >=3.8
